flowpipe/__init__.py
flowpipe/errors.py
flowpipe/evaluator.py
flowpipe/event.py
flowpipe/graph.py
flowpipe/node.py
flowpipe/plug.py
flowpipe/utilities.py
flowpipe-1.2.0.dist-info/METADATA
flowpipe-1.2.0.dist-info/WHEEL
flowpipe-1.2.0.dist-info/licenses/LICENSE
flowpipe-1.2.0.dist-info/RECORD
