Metadata-Version: 2.4
Name: Flowpipe
Version: 1.2.0
Summary: A lightweight framework for flow-based programming in python.
License-Expression: MIT
License-File: LICENSE
Author: Paul Schweizer
Author-email: paulschweizer@gmx.net
Requires-Python: >=3.9
Classifier: Programming Language :: Python :: 3
Classifier: Programming Language :: Python :: 3.9
Classifier: Programming Language :: Python :: 3.10
Classifier: Programming Language :: Python :: 3.11
Classifier: Programming Language :: Python :: 3.12
Classifier: Programming Language :: Python :: 3.13
Classifier: Programming Language :: Python :: 3.14
Classifier: Topic :: Software Development :: Build Tools
Classifier: Topic :: Software Development :: Libraries :: Python Modules
Requires-Dist: ascii-canvas (>=2.0.0)
Project-URL: Documentation, https://flowpipe.readthedocs.io/en/latest/
Project-URL: Repository, https://github.com/PaulSchweizer/flowpipe
